astrool/__init__.py
astrool/radec.py
astrool-0.1.dev0.dist-info/METADATA
astrool-0.1.dev0.dist-info/RECORD
astrool-0.1.dev0.dist-info/WHEEL
astrool-0.1.dev0.dist-info/entry_points.txt
astrool-0.1.dev0.dist-info/top_level.txt
