Metadata-Version: 2.1
Name: astrool
Version: 0.1.dev0
Summary: Python package for Astronomers in a Hurry
Home-page: http://shreyasb.com/
Author: Shreyas Bapat
Author-email: contact@shreyasb.com
License: MIT
Download-URL: https://github.com/shreyasbapat/astrool
Keywords: astro,positional,astronomy,ephem,orbits,every-astro,orbital mechanics
Platform: UNKNOWN
Classifier: Development Status :: 4 - Beta
Classifier: Intended Audience :: Education
Classifier: Intended Audience :: Science/Research
Classifier: License :: OSI Approved :: MIT License
Classifier: Operating System :: OS Independent
Classifier: Programming Language :: Python
Classifier: Programming Language :: Python :: 3
Classifier: Programming Language :: Python :: 3.5
Classifier: Programming Language :: Python :: 3.6
Classifier: Programming Language :: Python :: Implementation :: CPython
Classifier: Topic :: Scientific/Engineering
Classifier: Topic :: Scientific/Engineering :: Physics
Classifier: Topic :: Scientific/Engineering :: Astronomy
Requires-Python: >=3.5
Provides-Extra: dev
Requires-Dist: numpy
Requires-Dist: astropy (<4.*,>=3.0)
Requires-Dist: matplotlib (>=2.0)
Requires-Dist: ephem
Requires-Dist: scipy
Requires-Dist: beautifulsoup4 (>=4.5.3)
Requires-Dist: requests
Requires-Dist: pandas
Requires-Dist: plotly (<4.*,>=3.0)
Requires-Dist: astroquery (>=0.3.8)
Requires-Dist: numba (>=0.39); implementation_name=="cpython"
Provides-Extra: dev
Requires-Dist: coverage; extra == 'dev'
Requires-Dist: pytest-cov; extra == 'dev'
Requires-Dist: pycodestyle; extra == 'dev'
Requires-Dist: sphinx; extra == 'dev'
Requires-Dist: sphinx-rtd-theme; extra == 'dev'
Requires-Dist: nbsphinx; extra == 'dev'
Requires-Dist: ipython (>=5.0); extra == 'dev'
Requires-Dist: jupyter-client; extra == 'dev'
Requires-Dist: ipykernel; extra == 'dev'
Requires-Dist: ipywidgets; extra == 'dev'
